pyetr/__init__.py
pyetr/atoms/__init__.py
pyetr/atoms/abstract.py
pyetr/atoms/atom_likes.py
pyetr/atoms/doatom.py
pyetr/atoms/open_predicate_atom.py
pyetr/atoms/predicate.py
pyetr/atoms/predicate_atom.py
pyetr/atoms/terms/__init__.py
pyetr/atoms/terms/abstract_term.py
pyetr/atoms/terms/function.py
pyetr/atoms/terms/multiset.py
pyetr/atoms/terms/open_term.py
pyetr/atoms/terms/special_funcs.py
pyetr/atoms/terms/term.py
pyetr/cases.py
pyetr/dependency.py
pyetr/exceptions.py
pyetr/func_library.py
pyetr/inference.py
pyetr/issues.py
pyetr/parsing/common.py
pyetr/parsing/data_parser/__init__.py
pyetr/parsing/data_parser/model_to_view.py
pyetr/parsing/data_parser/models.py
pyetr/parsing/data_parser/view_to_model.py
pyetr/parsing/english_parser/__init__.py
pyetr/parsing/fol_items/__init__.py
pyetr/parsing/fol_items/items.py
pyetr/parsing/fol_items/items_to_view.py
pyetr/parsing/fol_items/view_to_items.py
pyetr/parsing/fol_parser/__init__.py
pyetr/parsing/fol_parser/parse_string.py
pyetr/parsing/fol_parser/unparse_item.py
pyetr/parsing/smt_lib_parser/__init__.py
pyetr/parsing/smt_lib_parser/smt_lib_to_view.py
pyetr/parsing/smt_lib_parser/view_to_smt_lib.py
pyetr/parsing/smt_parser/__init__.py
pyetr/parsing/smt_parser/parse_smt.py
pyetr/parsing/smt_parser/unparse_smt.py
pyetr/parsing/string_parser/__init__.py
pyetr/parsing/string_parser/parse_string.py
pyetr/parsing/string_parser/parse_view.py
pyetr/parsing/string_parser/unparse_view.py
pyetr/parsing/view_storage.py
pyetr/stateset.py
pyetr/tools.py
pyetr/types.py
pyetr/utils.py
pyetr/view.py
pyetr/weight.py
pyetr-1.0.0.dist-info/LICENSE
pyetr-1.0.0.dist-info/METADATA
pyetr-1.0.0.dist-info/WHEEL
pyetr-1.0.0.dist-info/entry_points.txt
pyetr-1.0.0.dist-info/RECORD
